Workbook

Sheet Assumptions
A1: BookFast Pty Ltd — Startup Financial Model
A2: Salon booking software. Twelve month plan from August 2026.
A3: Synthetic test file for the MamakScore AI engine. Not a real company.
A5: Key assumptions
A6: Assumption | B6: Value | C6: Basis
A7: Paying customers at start | B7: 500 | C7: Salons on a paid plan at 1 Aug 2026
A8: Monthly customer growth rate | B8: 0.08 | C8: Average of the last three months
A9: Average revenue per customer | B9: 40 | C9: Single flat subscription tier
A10: Gross margin | B10: 0.7 | C10: After hosting and card processing fees
A11: Operating expenses at start | B11: 25000 | C11: Salaries, marketing, rent, tools
A12: Monthly opex growth rate | B12: 0.03 | C12: Two hires planned in the period
A13: Opening cash balance | B13: 180000 | C13: Bank balance at 1 Aug 2026
A14: Customer acquisition cost | B14: 220 | C14: Sales and marketing / new customers
A15: Average customer lifetime (months) | B15: 30 | C15: Founder estimate, not yet observed
A17: Blue figures are typed in. Every other sheet is formulas.

Sheet Revenue Forecast
A1: Revenue forecast
B3: Aug 26 | C3: Sep 26 | D3: Oct 26 | E3: Nov 26 | F3: Dec 26 | G3: Jan 27 | H3: Feb 27 | I3: Mar 27 | J3: Apr 27 | K3: May 27 | L3: Jun 27 | M3: Jul 27
A4: Paying customers | B4: 500 | C4: 540 | D4: 583 | E4: 630 | F4: 680 | G4: 734 | H4: 793 | I4: 856 | J4: 924 | K4: 998 | L4: 1078 | M4: 1164
A5: Average revenue per customer | B5: =Assumptions!$B$9 -> 40 | C5: =Assumptions!$B$9 -> 40 | D5: =Assumptions!$B$9 -> 40 | E5: =Assumptions!$B$9 -> 40 | F5: =Assumptions!$B$9 -> 40 | G5: =Assumptions!$B$9 -> 40 | H5: =Assumptions!$B$9 -> 40 | I5: =Assumptions!$B$9 -> 40 | ... M5: =Assumptions!$B$9 -> 40
A6: Revenue | B6: =B4*B5 -> 20000 | C6: =C4*C5 -> 21600 | D6: =D4*D5 -> 23320 | E6: =E4*E5 -> 25200 | F6: =F4*F5 -> 27200 | G6: =G4*G5 -> 29360 | H6: =H4*H5 -> 31720 | I6: =I4*I5 -> 34240 | ... M6: =M4*M5 -> 46560
A7: Cost of goods sold | B7: =B6*(1-Assumptions!$B$10) -> 6000 | C7: =C6*(1-Assumptions!$B$10) -> 6480 | D7: =D6*(1-Assumptions!$B$10) -> 6996 | E7: =E6*(1-Assumptions!$B$10) -> 7560 | F7: =F6*(1-Assumptions!$B$10) -> 8160 | G7: =G6*(1-Assumptions!$B$10) -> 8808 | H7: =H6*(1-Assumptions!$B$10) -> 9516 | I7: =I6*(1-Assumptions!$B$10) -> 10272 | ... M7: =M6*(1-Assumptions!$B$10) -> 13968
A8: Gross profit | B8: =B6-B7 -> 14000 | C8: =C6-C7 -> 15120 | D8: =D6-D7 -> 16324 | E8: =E6-E7 -> 17640 | F8: =F6-F7 -> 19040 | G8: =G6-G7 -> 20552 | H8: =H6-H7 -> 22204 | I8: =I6-I7 -> 23968 | ... M8: =M6-M7 -> 32592
A10: Cost of goods sold is hosting, SMS and payment fees.

Sheet Operating Expenses
A1: Operating expenses
B3: Aug 26 | C3: Sep 26 | D3: Oct 26 | E3: Nov 26 | F3: Dec 26 | G3: Jan 27 | H3: Feb 27 | I3: Mar 27 | J3: Apr 27 | K3: May 27 | L3: Jun 27 | M3: Jul 27
A4: Salaries and contractors | B4: 15500 | C4: 15965 | D4: 16444 | E4: 16937 | F4: 17446 | G4: 17969 | H4: 18508 | I4: 19063 | J4: 19635 | K4: 20224 | L4: 20831 | M4: 21456
A5: Marketing | B5: 5500 | C5: 5665 | D5: 5835 | E5: 6010 | F5: 6190 | G5: 6376 | H5: 6567 | I5: 6764 | J5: 6967 | K5: 7176 | L5: 7392 | M5: 7613
A6: Rent, tools and other | B6: 4000 | C6: 4120 | D6: 4243 | E6: 4371 | F6: 4502 | G6: 4637 | H6: 4776 | I6: 4920 | J6: 5067 | K6: 5219 | L6: 5375 | M6: 5537
A7: Total operating expenses | B7: =SUM(B4:B6) -> 25000 | C7: =SUM(C4:C6) -> 25750 | D7: =SUM(D4:D6) -> 26522 | E7: =SUM(E4:E6) -> 27318 | F7: =SUM(F4:F6) -> 28138 | G7: =SUM(G4:G6) -> 28982 | H7: =SUM(H4:H6) -> 29851 | I7: =SUM(I4:I6) -> 30747 | ... M7: =SUM(M4:M6) -> 34606

Sheet P&L
A1: Profit and loss
B3: Aug 26 | C3: Sep 26 | D3: Oct 26 | E3: Nov 26 | F3: Dec 26 | G3: Jan 27 | H3: Feb 27 | I3: Mar 27 | J3: Apr 27 | K3: May 27 | L3: Jun 27 | M3: Jul 27
A4: Revenue | B4: ='Revenue Forecast'!B6 -> 20000 | C4: ='Revenue Forecast'!C6 -> 21600 | D4: ='Revenue Forecast'!D6 -> 23320 | E4: ='Revenue Forecast'!E6 -> 25200 | F4: ='Revenue Forecast'!F6 -> 27200 | G4: ='Revenue Forecast'!G6 -> 29360 | H4: ='Revenue Forecast'!H6 -> 31720 | I4: ='Revenue Forecast'!I6 -> 34240 | ... M4: ='Revenue Forecast'!M6 -> 46560
A5: Cost of goods sold | B5: ='Revenue Forecast'!B7 -> 6000 | C5: ='Revenue Forecast'!C7 -> 6480 | D5: ='Revenue Forecast'!D7 -> 6996 | E5: ='Revenue Forecast'!E7 -> 7560 | F5: ='Revenue Forecast'!F7 -> 8160 | G5: ='Revenue Forecast'!G7 -> 8808 | H5: ='Revenue Forecast'!H7 -> 9516 | I5: ='Revenue Forecast'!I7 -> 10272 | ... M5: ='Revenue Forecast'!M7 -> 13968
A6: Gross profit | B6: =B4-B5 -> 14000 | C6: =C4-C5 -> 15120 | D6: =D4-D5 -> 16324 | E6: =E4-E5 -> 17640 | F6: =F4-F5 -> 19040 | G6: =G4-G5 -> 20552 | H6: =H4-H5 -> 22204 | I6: =I4-I5 -> 23968 | ... M6: =M4-M5 -> 32592
A7: Operating expenses | B7: ='Operating Expenses'!B7 -> 25000 | C7: ='Operating Expenses'!C7 -> 25750 | D7: ='Operating Expenses'!D7 -> 26522 | E7: ='Operating Expenses'!E7 -> 27318 | F7: ='Operating Expenses'!F7 -> 28138 | G7: ='Operating Expenses'!G7 -> 28982 | H7: ='Operating Expenses'!H7 -> 29851 | I7: ='Operating Expenses'!I7 -> 30747 | ... M7: ='Operating Expenses'!M7 -> 34606
A8: EBITDA | B8: =B6-B7 -> -11000 | C8: =C6-C7 -> -10630 | D8: =D6-D7 -> -10198 | E8: =E6-E7 -> -9678 | F8: =F6-F7 -> -9098 | G8: =G6-G7 -> -8430 | H8: =H6-H7 -> -7647 | I8: =I6-I7 -> -6779 | ... M8: =M6-M7 -> -2014
A9: EBITDA margin | B9: =IFERROR(B8/B4,0) -> -0.55 | C9: =IFERROR(C8/C4,0) -> -0.49212963 | D9: =IFERROR(D8/D4,0) -> -0.43730703 | E9: =IFERROR(E8/E4,0) -> -0.38404762 | F9: =IFERROR(F8/F4,0) -> -0.33448529 | G9: =IFERROR(G8/G4,0) -> -0.28712534 | H9: =IFERROR(H8/H4,0) -> -0.24107818 | I9: =IFERROR(I8/I4,0) -> -0.19798481 | ... M9: =IFERROR(M8/M4,0) -> -0.043256014
A11: No depreciation or interest in the period, so EBITDA equals operating profit.

Sheet Cash Flow
A1: Cash flow
B3: Aug 26 | C3: Sep 26 | D3: Oct 26 | E3: Nov 26 | F3: Dec 26 | G3: Jan 27 | H3: Feb 27 | I3: Mar 27 | J3: Apr 27 | K3: May 27 | L3: Jun 27 | M3: Jul 27
A4: Opening cash | B4: =Assumptions!$B$13 -> 180000 | C4: =B7 -> 169000 | D4: =C7 -> 158370 | E4: =D7 -> 148172 | F4: =E7 -> 138494 | G4: =F7 -> 129396 | H4: =G7 -> 120966 | I4: =H7 -> 113319 | J4: =I7 -> 106540 | ... M4: =L7 -> 92654
A5: Cash from operations | B5: ='P&L'!B8 -> -11000 | C5: ='P&L'!C8 -> -10630 | D5: ='P&L'!D8 -> -10198 | E5: ='P&L'!E8 -> -9678 | F5: ='P&L'!F8 -> -9098 | G5: ='P&L'!G8 -> -8430 | H5: ='P&L'!H8 -> -7647 | I5: ='P&L'!I8 -> -6779 | ... M5: ='P&L'!M8 -> -2014
A6: Net burn | B6: =-B5 -> 11000 | C6: =-C5 -> 10630 | D6: =-D5 -> 10198 | E6: =-E5 -> 9678 | F6: =-F5 -> 9098 | G6: =-G5 -> 8430 | H6: =-H5 -> 7647 | I6: =-I5 -> 6779 | ... M6: =-M5 -> 2014
A7: Closing cash | B7: =B4+B5 -> 169000 | C7: =C4+C5 -> 158370 | D7: =D4+D5 -> 148172 | E7: =E4+E5 -> 138494 | F7: =F4+F5 -> 129396 | G7: =G4+G5 -> 120966 | H7: =H4+H5 -> 113319 | I7: =I4+I5 -> 106540 | ... M7: =M4+M5 -> 90640
A9: Net burn is positive when the company is losing money.

Sheet Funding Requirements
A1: Funding requirements
A3: Item | B3: Value | C3: Note
A4: Monthly net burn (month 1) | B4: ='Cash Flow'!B6 -> 11000 | C4: Operating expenses less gross profit
A5: Runway at current burn (months) | B5: =IFERROR(Assumptions!B13/'Cash Flow'!B6,"n/a") -> 16.363636 | C5: Opening cash divided by month one burn
A6: Cash at month 12 | B6: ='Cash Flow'!M7 -> 90640 | C6: Closing balance on the cash flow
A7: Amount sought | B7: 500000 | C7: Pre-seed round
A8: Use of funds — engineering | B8: 250000 | C8: Two engineers for eighteen months
A9: Use of funds — sales and marketing | B9: 175000 | C9: Channel partnerships and paid acquisition
A10: Use of funds — working capital | B10: 75000 | C10: Buffer
A11: Total use of funds | B11: =SUM(B8:B10) -> 500000
